run.py
profiler_wrapper-1.0.1.dist-info/LICENSE.txt
profiler_wrapper-1.0.1.dist-info/METADATA
profiler_wrapper-1.0.1.dist-info/WHEEL
profiler_wrapper-1.0.1.dist-info/top_level.txt
profiler_wrapper-1.0.1.dist-info/RECORD
