Metadata-Version: 2.1
Name: profiler-wrapper
Version: 1.0.1
Summary: Wrapper script for easier use of the built-in profiler
Home-page: https://github.com/superstes/python3-profile-wrapper
Author: René Rath
Author-email: contact@superstes.eu
Project-URL: Repository, https://github.com/superstes/python3-profile-wrapper
Project-URL: Bug Tracker, https://github.com/superstes/python3-profile-wrapper/issues
Classifier: Programming Language :: Python :: 3
Classifier: License :: OSI Approved :: GNU General Public License v3 (GPLv3)
Classifier: Operating System :: OS Independent
Requires-Python: >=3.3
License-File: LICENSE.txt
